pytest_metrics/__init__.py
pytest_metrics/plugin.py
pytest_metrics-0.4.dist-info/LICENSE
pytest_metrics-0.4.dist-info/METADATA
pytest_metrics-0.4.dist-info/WHEEL
pytest_metrics-0.4.dist-info/entry_points.txt
pytest_metrics-0.4.dist-info/top_level.txt
pytest_metrics-0.4.dist-info/zip-safe
pytest_metrics-0.4.dist-info/RECORD
